phorama/__init__.py
phorama/enhance.py
phorama/models/SRGAN.py
phorama/models/__init__.py
phorama/models/model.py
tests/__init__.py
phorama-0.0.2.dist-info/LICENSE
phorama-0.0.2.dist-info/METADATA
phorama-0.0.2.dist-info/WHEEL
phorama-0.0.2.dist-info/top_level.txt
phorama-0.0.2.dist-info/RECORD
